tests/__init__.py
tests/test_checkers.py
tests/test_pdchecker.py
pdcheckers-0.1.dist-info/LICENSE
pdcheckers-0.1.dist-info/METADATA
pdcheckers-0.1.dist-info/WHEEL
pdcheckers-0.1.dist-info/top_level.txt
pdcheckers-0.1.dist-info/RECORD
